ebook_tree_parser/toctree.py
ebook_tree_parser-0.1.2.dist-info/LICENSE
ebook_tree_parser-0.1.2.dist-info/METADATA
ebook_tree_parser-0.1.2.dist-info/WHEEL
ebook_tree_parser-0.1.2.dist-info/top_level.txt
ebook_tree_parser-0.1.2.dist-info/RECORD
