Metadata-Version: 2.1
Name: ebook-tree-parser
Version: 0.1.2
Summary: Parse an ebook based on its TOC into a tree-like structure
Author-email: Jimmy Yao <jinghaoyao@gmail.com>
License: MIT License
Requires-Python: >=3.10
License-File: LICENSE
Requires-Dist: EbookLib >=0.18
Requires-Dist: beautifulsoup4 >=4.12.3
Requires-Dist: html2text >=2024.2.26
Requires-Dist: tiktoken >=0.7.0
